pyuart/__init__.py
pyuart-0.1.1.dist-info/METADATA
pyuart-0.1.1.dist-info/WHEEL
pyuart-0.1.1.dist-info/top_level.txt
pyuart-0.1.1.dist-info/RECORD
